password_smelter/__init__.py
password_smelter/lib/assets/styles.css
password_smelter/lib/report.py
password_smelter/lib/stat.py
password_smelter/smelter.py
password_smelter-1.0.8.dist-info/LICENSE
password_smelter-1.0.8.dist-info/METADATA
password_smelter-1.0.8.dist-info/WHEEL
password_smelter-1.0.8.dist-info/entry_points.txt
password_smelter-1.0.8.dist-info/RECORD
